covxnet/__init__.py
covxnet/version.py
covxnet/blocks/__init__.py
covxnet/blocks/residual.py
covxnet/blocks/shifter.py
covxnet/blocks/stem.py
covxnet/network/__init__.py
covxnet/network/model.py
covxnet-1.0.0.dist-info/LICENSE
covxnet-1.0.0.dist-info/METADATA
covxnet-1.0.0.dist-info/WHEEL
covxnet-1.0.0.dist-info/top_level.txt
covxnet-1.0.0.dist-info/RECORD
