Metadata-Version: 2.1
Name: covxnet
Version: 1.0.0
Summary: Official Implementation of CovXNet using Tensorflow 2.0
Home-page: https://github.com/awsaf49/CovXNet
Author: Awsaf
Author-email: awsaf49@gmail.com
License: Apache License 2.0
Keywords: cnn computer_vision covid19 medical_imaging
Classifier: Development Status :: 3 - Alpha
Classifier: Intended Audience :: Developers
Classifier: Intended Audience :: Science/Research
Classifier: License :: OSI Approved :: Apache Software License
Classifier: Programming Language :: Python :: 3.6
Classifier: Programming Language :: Python :: 3.7
Classifier: Programming Language :: Python :: 3.8
Classifier: Topic :: Scientific/Engineering
Classifier: Topic :: Scientific/Engineering :: Artificial Intelligence
Classifier: Topic :: Software Development
Classifier: Topic :: Software Development :: Libraries
Classifier: Topic :: Software Development :: Libraries :: Python Modules
Requires-Python: >=3.6
License-File: LICENSE
Requires-Dist: tensorflow (>=2.3)
